hpfitter/__init__.py
hpfitter/hpfitter.py
hpfitter/hpboundary/__init__.py
hpfitter/hpboundary/boundary.py
hpfitter/hpboundary/educated.py
hpfitter/hpboundary/hptrans.py
hpfitter/hpboundary/length.py
hpfitter/hpboundary/restricted.py
hpfitter/hpboundary/strict.py
hpfitter/means/__init__.py
hpfitter/means/constant.py
hpfitter/means/first.py
hpfitter/means/max.py
hpfitter/means/mean.py
hpfitter/means/median.py
hpfitter/means/min.py
hpfitter/means/prior.py
hpfitter/objectivefunctions/__init__.py
hpfitter/objectivefunctions/factorized_likelihood.py
hpfitter/objectivefunctions/likelihood.py
hpfitter/objectivefunctions/mle.py
hpfitter/objectivefunctions/objectivefunction.py
hpfitter/objectivefunctions/objectivefunction_gpatom.py
hpfitter/optimizers/__init__.py
hpfitter/optimizers/globaloptimizer.py
hpfitter/optimizers/linesearcher.py
hpfitter/optimizers/localoptimizer.py
hpfitter/optimizers/noisesearcher.py
hpfitter/optimizers/optimizer.py
hpfitter/pdistributions/__init__.py
hpfitter/pdistributions/gamma.py
hpfitter/pdistributions/gen_normal.py
hpfitter/pdistributions/invgamma.py
hpfitter/pdistributions/normal.py
hpfitter/pdistributions/pdistributions.py
hpfitter/pdistributions/uniform.py
hpfitter/pdistributions/update_pdis.py
hpfitter-5.0.0.dist-info/LICENSE.txt
hpfitter-5.0.0.dist-info/METADATA
hpfitter-5.0.0.dist-info/WHEEL
hpfitter-5.0.0.dist-info/top_level.txt
hpfitter-5.0.0.dist-info/RECORD
