Metadata-Version: 2.1
Name: hpfitter
Version: 5.0.0
Summary: Hyperparameter fitter for the Gaussian Process from GP-atom
Author-email: Andreas Vishart <alyvi@dtu.dk>
Project-URL: Homepage, https://github.com/avishart/hpfitter
Classifier: Development Status :: 3 - Alpha
Classifier: Intended Audience :: Education
Classifier: Programming Language :: Python :: 3
Classifier: License :: OSI Approved :: GNU General Public License (GPL)
Classifier: Operating System :: MacOS
Classifier: Operating System :: POSIX :: Linux
Requires-Python: >=3.7
License-File: LICENSE.txt
Requires-Dist: numpy >=1.20.3
Requires-Dist: scipy >=1.8.0
Requires-Dist: ase >=3.22.1
